tyranobot/__init__.py
tyranobot/tyranobot.py
tyranobot-0.2.0.dist-info/DESCRIPTION.rst
tyranobot-0.2.0.dist-info/LICENSE.txt
tyranobot-0.2.0.dist-info/METADATA
tyranobot-0.2.0.dist-info/metadata.json
tyranobot-0.2.0.dist-info/RECORD
tyranobot-0.2.0.dist-info/top_level.txt
tyranobot-0.2.0.dist-info/WHEEL
