Metadata-Version: 2.0
Name: tyranobot
Version: 0.2.0
Summary: Easily customizable Slackbot
Home-page: https://github.com/jperezlatimes/tyranobot
Author: James Perez
Author-email: james.perez@tronc.com
License: GNU GENERAL PUBLIC LICENSE
Platform: UNKNOWN
Classifier: Development Status :: 4 - Beta
Classifier: Intended Audience :: Developers
Classifier: Programming Language :: Python :: 2.7
Classifier: Intended Audience :: Developers
Classifier: Topic :: Communications :: Chat
